lenspy/GraphQLClient.py
lenspy/LensPy.py
lenspy/__init__.py
lenspy/helpers.py
lenspy/lens-api.documents.graphql
lenspy/lens-api.schema.graphql
lenspy/parse_graphql.py
LensProtocolPy-0.1.2.dist-info/METADATA
LensProtocolPy-0.1.2.dist-info/WHEEL
LensProtocolPy-0.1.2.dist-info/top_level.txt
LensProtocolPy-0.1.2.dist-info/RECORD
