Metadata-Version: 2.1
Name: LensProtocolPy
Version: 0.1.2
Summary: A python library for working with Lens Protocol
Author: Rishin Madan and Tobias Loader
License: MIT
Requires-Dist: gql
Requires-Dist: requests-toolbelt
